oci_enum/__init__.py
oci_enum/command_line.py
oci_enum/instance_metdata_config.py
oci_enum/oci_enumerator.py
oci_enum-0.1.1.dist-info/LICENSE
oci_enum-0.1.1.dist-info/METADATA
oci_enum-0.1.1.dist-info/WHEEL
oci_enum-0.1.1.dist-info/entry_points.txt
oci_enum-0.1.1.dist-info/top_level.txt
oci_enum-0.1.1.dist-info/RECORD
