Metadata-Version: 2.1
Name: oci-enum
Version: 0.1.1
Summary: CLI Tool by Orca Security to enumerate services in Oracle Cloud Infrastructure
Home-page: https://github.com/orcasecurity/orca-toolbox/tree/main/oci_enum
Author: Lidor Ben Shitrit, Tohar Braun
Author-email: lidor@orca.security, tohar@orca.security
License: MIT
Platform: UNKNOWN
Classifier: Development Status :: 3 - Alpha
Classifier: Intended Audience :: Developers
Classifier: Intended Audience :: System Administrators
Classifier: License :: OSI Approved :: MIT License
Classifier: Programming Language :: Python :: 3
Classifier: Topic :: Security
License-File: LICENSE
Requires-Dist: oci
Requires-Dist: texttable
